strip_tags/__init__.py
strip_tags/__main__.py
strip_tags/cli.py
strip_tags/lib.py
strip_tags-0.6.dist-info/LICENSE
strip_tags-0.6.dist-info/METADATA
strip_tags-0.6.dist-info/WHEEL
strip_tags-0.6.dist-info/entry_points.txt
strip_tags-0.6.dist-info/top_level.txt
strip_tags-0.6.dist-info/RECORD
