Metadata-Version: 2.2
Name: strip-tags
Version: 0.6
Summary: Strip tags from HTML, optionally from areas identified by CSS selectors
Home-page: https://github.com/simonw/strip-tags
Author: Simon Willison
License: Apache License, Version 2.0
Project-URL: Issues, https://github.com/simonw/strip-tags/issues
Project-URL: CI, https://github.com/simonw/strip-tags/actions
Project-URL: Changelog, https://github.com/simonw/strip-tags/releases
Requires-Python: >=3.7
License-File: LICENSE
Requires-Dist: click
Requires-Dist: beautifulsoup4
Requires-Dist: html5lib
Provides-Extra: test
Requires-Dist: pytest; extra == "test"
Requires-Dist: PyYAML; extra == "test"
Requires-Dist: cogapp; extra == "test"
Dynamic: author
Dynamic: description
Dynamic: description-content-type
Dynamic: home-page
Dynamic: license
Dynamic: project-url
Dynamic: provides-extra
Dynamic: requires-dist
Dynamic: requires-python
Dynamic: summary
